pupil_labs/invisible_lsl_relay/__init__.py
pupil_labs/invisible_lsl_relay/__main__.py
pupil_labs/invisible_lsl_relay/channels.py
pupil_labs/invisible_lsl_relay/cli.py
pupil_labs/invisible_lsl_relay/linear_time_model.py
pupil_labs/invisible_lsl_relay/outlets.py
pupil_labs/invisible_lsl_relay/relay.py
pupil_labs/invisible_lsl_relay/xdf_cloud_time_sync.py
pupil_invisible_lsl_relay-3.0.2.dist-info/LICENSE
pupil_invisible_lsl_relay-3.0.2.dist-info/METADATA
pupil_invisible_lsl_relay-3.0.2.dist-info/WHEEL
pupil_invisible_lsl_relay-3.0.2.dist-info/entry_points.txt
pupil_invisible_lsl_relay-3.0.2.dist-info/top_level.txt
pupil_invisible_lsl_relay-3.0.2.dist-info/RECORD
